MANIFEST.in
README.txt
setup.cfg
setup.py
docs/HISTORY.txt
docs/INSTALL.txt
docs/LICENSE.GPL
docs/LICENSE.txt
plonetheme/__init__.py
plonetheme.flowerbuds.egg-info/PKG-INFO
plonetheme.flowerbuds.egg-info/SOURCES.txt
plonetheme.flowerbuds.egg-info/dependency_links.txt
plonetheme.flowerbuds.egg-info/entry_points.txt
plonetheme.flowerbuds.egg-info/namespace_packages.txt
plonetheme.flowerbuds.egg-info/not-zip-safe
plonetheme.flowerbuds.egg-info/paster_plugins.txt
plonetheme.flowerbuds.egg-info/requires.txt
plonetheme.flowerbuds.egg-info/top_level.txt
plonetheme/flowerbuds/__init__.py
plonetheme/flowerbuds/configure.zcml
plonetheme/flowerbuds/tests.py
plonetheme/flowerbuds/theme/flowerbuds/index.html
plonetheme/flowerbuds/theme/flowerbuds/license.txt
plonetheme/flowerbuds/theme/flowerbuds/manifest.cfg
plonetheme/flowerbuds/theme/flowerbuds/public.css
plonetheme/flowerbuds/theme/flowerbuds/rules.xml
plonetheme/flowerbuds/theme/flowerbuds/style.css
plonetheme/flowerbuds/theme/flowerbuds/images/img01.jpg
plonetheme/flowerbuds/theme/flowerbuds/images/img02.jpg
plonetheme/flowerbuds/theme/flowerbuds/images/img03.jpg
plonetheme/flowerbuds/theme/flowerbuds/images/img04.jpg
plonetheme/flowerbuds/theme/flowerbuds/images/img05.jpg