Metadata-Version: 1.0
Name: plonetheme.flowerbuds
Version: 1.0
Summary: UNKNOWN
Home-page: http://svn.plone.org/svn/collective/
Author: JeanMichel FRANCOIS aka toutpt
Author-email: toutpt@gmail.com
License: GPL
Platform: UNKNOWN
Classifier: Framework :: Plone
Classifier: Programming Language :: Python
